skyportal_spatial/__init__.py
skyportal_spatial/none.py
skyportal_spatial/postgis.py
skyportal_spatial/q3c.py
skyportal_spatial-0.1.0.dist-info/LICENSE
skyportal_spatial-0.1.0.dist-info/METADATA
skyportal_spatial-0.1.0.dist-info/WHEEL
skyportal_spatial-0.1.0.dist-info/top_level.txt
skyportal_spatial-0.1.0.dist-info/RECORD
